setup.py
epa/__init__.py
epa.egg-info/PKG-INFO
epa.egg-info/SOURCES.txt
epa.egg-info/dependency_links.txt
epa.egg-info/top_level.txt
epa/envirofacts/__init__.py
epa/envirofacts/envirofacts_api.py
epa/envirofacts/api/__init__.py
epa/envirofacts/api/api.py
epa/envirofacts/api/test_api.py
epa/envirofacts/api/xml2dict/__init__.py
epa/envirofacts/api/xml2dict/object_dict.py
epa/envirofacts/api/xml2dict/xml2dict.py
epa/gics/__init__.py
epa/gics/gics.py
epa/gics/lookup_table.py
epa/pcs/__init__.py
epa/pcs/lookup_table.py
epa/pcs/pcs.py
epa/radinfo/__init__.py
epa/radinfo/lookup_table.py
epa/radinfo/radinfo.py
epa/tests/__init__.py
epa/tests/test_envirofacts.py
epa/tests/test_gics.py
epa/tests/test_pcs.py
epa/tests/test_radinfo.py