Metadata-Version: 1.0
Name: epa
Version: 1.3
Summary: Python wrapper for the multiple APIs available through the EPA's website.
Home-page: https://github.com/codeforamerica/epa_python
Author: Zach Williams
Author-email: zach@codeforamerica.org
License: BSD
Keywords: epa,EPA,environment
Platform: UNKNOWN
Classifier: Development Status :: 5 - Production/Stable
Classifier: Intended Audience :: Developers
Classifier: Natural Language :: English
Classifier: Operating System :: OS Independent
Classifier: Programming Language :: Python :: 2
Classifier: Topic :: Internet
Classifier: Topic :: Internet :: WWW/HTTP
